{
   "bids": [
      {
         "bundle": [
            0.0,
            0.0,
            0.0,
            0.0,
            0.0
         ],
         "value": {
            "sValue": 0.0,
            "tValue": 0.0
         }
      },
      {
         "bundle": [
            0.0,
            0.0,
            0.0,
            0.0,
            0.0
         ],
         "value": {
            "sValue": 0.0,
            "tValue": 0.0
         }
      },
      {
         "bundle": [
            0.0,
            0.0,
            283.5645949116175,
            0.0,
            0.0
         ],
         "value": {
            "sValue": 0.0,
            "tValue": 0.13538040059300507
         }
      },
      {
         "bundle": [
            0.0,
            0.0,
            0.0,
            0.0,
            0.0
         ],
         "value": {
            "sValue": 0.0,
            "tValue": 0.0
         }
      },
      {
         "bundle": [
            0.0,
            0.0,
            0.0,
            0.0,
            0.0
         ],
         "value": {
            "sValue": 0.0,
            "tValue": 0.0
         }
      }
   ]
}{
   "bids": [
      {
         "bundle": [
            0.0,
            0.0,
            0.0,
            0.0
         ],
         "value": {
            "sValue": 0.0,
            "tValue": 0.0
         }
      },
      {
         "bundle": [
            0.0,
            219.85355509881074,
            0.0,
            0.0
         ],
         "value": {
            "sValue": 0.0,
            "tValue": 0.13516899617327957
         }
      },
      {
         "bundle": [
            0.0,
            0.0,
            0.0,
            0.0
         ],
         "value": {
            "sValue": 0.0,
            "tValue": 0.0
         }
      },
      {
         "bundle": [
            0.0,
            0.0,
            0.0,
            0.0
         ],
         "value": {
            "sValue": 0.0,
            "tValue": 0.0
         }
      }
   ]
}